qcrypto/__init__.py
qcrypto/cli.py
qcrypto/hybrid.py
qcrypto/kem.py
qcrypto/keywrap.py
qcrypto/signatures.py
qcrypto-0.5.0.dist-info/licenses/LICENSE
qcrypto-0.5.0.dist-info/METADATA
qcrypto-0.5.0.dist-info/WHEEL
qcrypto-0.5.0.dist-info/entry_points.txt
qcrypto-0.5.0.dist-info/top_level.txt
qcrypto-0.5.0.dist-info/RECORD
