Metadata-Version: 2.4
Name: qcrypto
Version: 0.5.0
Summary: Quantum-safe cryptography utilities built on top of liboqs-python
Author-email: Victor Postea <victorpostea@gmail.com>
License: MIT
Project-URL: Repository, https://github.com/victorpostea/qcrypto
Requires-Python: >=3.8
License-File: LICENSE
Requires-Dist: liboqs-python>=0.14.0
Requires-Dist: cryptography>=41.0.0
Dynamic: license-file
